randomfun/__init__.py
randomfun/simple.py
randomfun-0.1.0.dist-info/LICENSE.txt
randomfun-0.1.0.dist-info/METADATA
randomfun-0.1.0.dist-info/WHEEL
randomfun-0.1.0.dist-info/entry_points.txt
randomfun-0.1.0.dist-info/top_level.txt
randomfun-0.1.0.dist-info/RECORD
