Metadata-Version: 2.1
Name: randomfun
Version: 0.1.0
Summary: A sample Python project
Author-email: "A. Random Developer" <author@example.com>
Maintainer-email: "A. Great Maintainer" <maintainer@example.com>
License: 
Keywords: sample,setuptools,development
Requires-Python: >=3.8
License-File: LICENSE.txt
Requires-Dist: numpy
Provides-Extra: dev
Requires-Dist: check-manifest ; extra == 'dev'
Provides-Extra: test
Requires-Dist: coverage ; extra == 'test'
